notification_client/__init__.py
notification_client/exceptions.py
notification_client/serializers.py
notification_client/utils.py
pebble_notification_client-2.0.0.dist-info/DESCRIPTION.rst
pebble_notification_client-2.0.0.dist-info/METADATA
pebble_notification_client-2.0.0.dist-info/RECORD
pebble_notification_client-2.0.0.dist-info/WHEEL
pebble_notification_client-2.0.0.dist-info/metadata.json
pebble_notification_client-2.0.0.dist-info/top_level.txt
