Metadata-Version: 2.0
Name: pebble-notification-client
Version: 2.0.0
Summary: SQS client for Pebble's notification-centre
Home-page: https://github.com/mypebble/notification-client
Author: Pebble
Author-email: tom.picton@talktopebble.co.uk
License: MIT
Platform: UNKNOWN
Requires-Dist: queue-fetcher
Requires-Dist: boto3
Requires-Dist: Django
Requires-Dist: djangorestframework
Requires-Dist: six
